MissForestExtra/__init__.py
MissForestExtra-1.1.1.dist-info/LICENSE.txt
MissForestExtra-1.1.1.dist-info/METADATA
MissForestExtra-1.1.1.dist-info/WHEEL
MissForestExtra-1.1.1.dist-info/top_level.txt
MissForestExtra-1.1.1.dist-info/RECORD
