Metadata-Version: 2.1
Name: MissForestExtra
Version: 1.1.1
Summary: nonparametric imputation on missing values.
Home-page: https://github.com/HindyDS/MissForestExtra
Author: Hindy Yuen
Author-email: hindy888@hotmail.com
License: MIT
Keywords: MissForest MissForestExtra aims to provide the most convenient way for the data science community to perform nonparametric imputation on missing values by using machine learning models
Platform: UNKNOWN
Classifier: Development Status :: 5 - Production/Stable
Classifier: Intended Audience :: Developers
Classifier: Topic :: Software Development :: Build Tools
Classifier: License :: OSI Approved :: MIT License
Classifier: Programming Language :: Python :: 3.7
Classifier: Programming Language :: Python :: 3.8
Classifier: Programming Language :: Python :: 3.9
Requires-Python: >=3.6
License-File: LICENSE.txt
